umbraSnscrpe/__init__.py
umbraSnscrpe/_cli.py
umbraSnscrpe/base.py
umbraSnscrpe/version.py
umbraSnscrpe/modules/__init__.py
umbraSnscrpe/modules/facebook.py
umbraSnscrpe/modules/instagram.py
umbraSnscrpe/modules/mastodon.py
umbraSnscrpe/modules/reddit.py
umbraSnscrpe/modules/telegram.py
umbraSnscrpe/modules/twitter.py
umbraSnscrpe/modules/vkontakte.py
umbraSnscrpe/modules/weibo.py
umbraSnscrpe-0.1.1.dist-info/LICENSE
umbraSnscrpe-0.1.1.dist-info/METADATA
umbraSnscrpe-0.1.1.dist-info/WHEEL
umbraSnscrpe-0.1.1.dist-info/top_level.txt
umbraSnscrpe-0.1.1.dist-info/RECORD
