Metadata-Version: 2.1
Name: umbraSnscrpe
Version: 0.1.1
Summary: UNKNOWN
Home-page: UNKNOWN
Author: umbra
Author-email: 
License: UNKNOWN
Keywords: lxml,requests[socks],beautifulsoup4,pytz; python_version < "3.9.0",filelock
Platform: UNKNOWN
Classifier: Development Status :: 4 - Beta
Classifier: License :: OSI Approved :: GNU General Public License v3 or later (GPLv3+)
Classifier: Programming Language :: Python :: 3.8
Classifier: Programming Language :: Python :: 3.9
Classifier: Programming Language :: Python :: 3.10
Classifier: Programming Language :: Python :: 3.11
Requires-Dist: beautifulsoup4
Requires-Dist: filelock
Requires-Dist: lxml
Requires-Dist: requests[socks]
Requires-Dist: pytz ; python_version < "3.9.0"
